iubeo/__init__.py
iubeo/casters.py
iubeo/config.py
iubeo/exceptions.py
iubeo-0.4.1.dist-info/LICENCE
iubeo-0.4.1.dist-info/METADATA
iubeo-0.4.1.dist-info/WHEEL
iubeo-0.4.1.dist-info/RECORD
