Metadata-Version: 2.3
Name: iubeo
Version: 0.4.1
Summary: Friendlier way to write your config.
License: MIT
Keywords: config,configuration,environment
Author: Işık Kaplan
Author-email: isik.kaplan@outlook.com
Requires-Python: >=3.5
Classifier: Topic :: Software Development
Classifier: License :: OSI Approved :: MIT License
Classifier: Programming Language :: Python :: 3
Classifier: Development Status :: 5 - Production/Stable
Provides-Extra: dev
Requires-Dist: pre-commit (>=2.9.3) ; extra == "dev"
Requires-Dist: pytest (>=5.2) ; extra == "dev"
Project-URL: Documentation, https://github.com/isik-kaplan/iubeo
Project-URL: Homepage, https://github.com/isik-kaplan/iubeo
Project-URL: Repository, https://github.com/isik-kaplan/iubeo
